cursofiap/__init__.py
cursofiap/core.py
iissa_cursofiap_package-1.0.0.dist-info/METADATA
iissa_cursofiap_package-1.0.0.dist-info/WHEEL
iissa_cursofiap_package-1.0.0.dist-info/top_level.txt
iissa_cursofiap_package-1.0.0.dist-info/RECORD
