Metadata-Version: 2.1
Name: iissa-cursofiap-package
Version: 1.0.0
Summary: Descricao da sua lib cursofiap
Home-page: https://github.com/ivanissa/cursofiap
Author: Ivan Alfredo Issa
Author-email: ivanissa.dev@gmail.com
License: MIT
Platform: UNKNOWN
